covid19BD
