Metadata-Version: 2.1
Name: covid19BD
Version: 1.0.0
Summary: It lets you interact with my database created by Covid-19 Bot hosted on repl.it for Bangladesh from 15th January 2021 - Current Day.
Home-page: UNKNOWN
Author: Arib Muhtasim
Author-email: aribmuhtasim22@gmail.com
License: MIT
Keywords: Covid-19,Coronavirus
Platform: UNKNOWN
Classifier: Development Status :: 2 - Pre-Alpha
Classifier: Intended Audience :: Education
Classifier: Operating System :: Microsoft :: Windows :: Windows 10
Classifier: License :: OSI Approved :: MIT License
Classifier: Programming Language :: Python :: 3
